synthpops/__init__.py
synthpops/base.py
synthpops/config.py
synthpops/contact_networks.py
synthpops/data.py
synthpops/data_distributions.py
synthpops/defaults.py
synthpops/households.py
synthpops/ltcfs.py
synthpops/plotting.py
synthpops/pop.py
synthpops/sampling.py
synthpops/schools.py
synthpops/version.py
synthpops/workplaces.py
synthpops/data/MUestimates_all_locations.obj
synthpops/data/MUestimates_home.obj
synthpops/data/MUestimates_other_locations.obj
synthpops/data/MUestimates_school.obj
synthpops/data/MUestimates_work.obj
synthpops/data/Malawi.json
synthpops/data/Nepal.json
synthpops/data/Senegal-Dakar-Dakar.json
synthpops/data/Senegal-Dakar.json
synthpops/data/Senegal.json
synthpops/data/Zimbabwe.json
synthpops/data/bangladesh-dhaka-dhaka_city.json
synthpops/data/usa-Oregon-portland_metro.json
synthpops/data/usa-Oregon.json
synthpops/data/usa-Washington-Franklin_County.json
synthpops/data/usa-Washington-Island_County.json
synthpops/data/usa-Washington-Spokane_County.json
synthpops/data/usa-Washington-seattle_metro.json
synthpops/data/usa-Washington.json
synthpops/data/usa.json
synthpops/people/__init__.py
synthpops/people/country_age_data.py
synthpops/people/household_size_data.py
synthpops/people/loaders.py
synthpops/people/makepop.py
synthpops/people/people.py
synthpops/people/state_age_data.py
synthpops/people/utils.py
synthpops-1.10.5.dist-info/LICENSE
synthpops-1.10.5.dist-info/METADATA
synthpops-1.10.5.dist-info/WHEEL
synthpops-1.10.5.dist-info/top_level.txt
synthpops-1.10.5.dist-info/RECORD
