Metadata-Version: 2.1
Name: synthpops
Version: 1.10.5
Summary: Synthetic contact network generation
Home-page: http://synthpops.org
Author: Dina Mistry, Cliff Kerr, Meikang Wu, Mary Fisher, Ace Thompson, and Daniel Klein on behalf of the IDM COVID-19 Response Team
Author-email: covid@idmod.org
Keywords: human contact networks,synthetic population,age mixing patterns,census,demography
Platform: OS Independent
Classifier: Environment :: Console
Classifier: Intended Audience :: Science/Research
Classifier: License :: Other/Proprietary License
Classifier: Operating System :: OS Independent
Classifier: Programming Language :: Python
Classifier: Topic :: Software Development :: Libraries :: Python Modules
Classifier: Development Status :: 4 - Beta
Classifier: Programming Language :: Python :: 3.7
Classifier: Programming Language :: Python :: 3.8
License-File: LICENSE
Requires-Dist: sciris (>=1.1.1)
Requires-Dist: matplotlib (>=3.3.0)
Requires-Dist: numpy
Requires-Dist: scipy
Requires-Dist: pandas (>=1.2.3)
Requires-Dist: numba
Requires-Dist: networkx (>=2.3)
Requires-Dist: cmocean
Requires-Dist: cmasher
Requires-Dist: seaborn
Requires-Dist: graphviz
Requires-Dist: pydot
Requires-Dist: jsonobject
Requires-Dist: jsbeautifier
